elaugment/__init__.py
elaugment/generator.py
elaugment/random.py
elaugment/transformations.py
elaugment/image/__init__.py
elaugment/image/random.py
elaugment/image/transformations.py
elaugment-0.1.0.dist-info/LICENSE
elaugment-0.1.0.dist-info/METADATA
elaugment-0.1.0.dist-info/WHEEL
elaugment-0.1.0.dist-info/top_level.txt
elaugment-0.1.0.dist-info/RECORD
