Metadata-Version: 2.1
Name: elaugment
Version: 0.1.0
Summary: A lightweight data-augmentation library for machine learning
Home-page: https://github.com/Mctigger/elaugment
Author: Tim Joseph
License: MIT
Platform: UNKNOWN
Classifier: Programming Language :: Python
Classifier: Programming Language :: Python :: 3.6
Requires-Python: >=3.6
Requires-Dist: numpy
Requires-Dist: scikit-image
Requires-Dist: scipy
